aipose/__init__.py
aipose/__main__.py
aipose/downloader/__init__.py
aipose/filters/__init__.py
aipose/frame/__init__.py
aipose/frame/frame_manager_base.py
aipose/frame/frame_plot.py
aipose/frame/frame_yolo_v7.py
aipose/models/__init__.py
aipose/models/yolov7/__init__.py
aipose/models/yolov7/domain.py
aipose/models/yolov7/types.py
aipose/plot.py
aipose/stream/__init__.py
aipose/utils.py
aipose-3.1.0.dist-info/LICENSE.txt
aipose-3.1.0.dist-info/METADATA
aipose-3.1.0.dist-info/WHEEL
aipose-3.1.0.dist-info/entry_points.txt
aipose-3.1.0.dist-info/RECORD
